makana_model/__init__.py
makana_model/_version.py
makana_model/labextension/package.json
makana_model/labextension/static/568.753df48067f9c12f7dce.js
makana_model/labextension/static/747.2cf1ef1833753e94fb57.js
makana_model/labextension/static/remoteEntry.4f0b220e71075ccf8dcb.js
makana_model/labextension/static/style.js
makana_model/labextension/static/third-party-licenses.json
makana_model/nbextension/README.md
makana_model/nbextension/jupytext_menu.png
makana_model/nbextension/main.css
makana_model/nbextension/main.js
makana_model/nbextension/makanamodel.yaml
makana_model-0.1.0.data/data/etc/jupyter/jupyter_notebook_config.d/makana_model.json
makana_model-0.1.0.data/data/etc/jupyter/jupyter_server_config.d/makana_model.json
makana_model-0.1.0.data/data/etc/jupyter/nbconfig/notebook.d/makana_model.json
makana_model-0.1.0.data/data/share/jupyter/nbextensions/makana_model/README.md
makana_model-0.1.0.data/data/share/jupyter/nbextensions/makana_model/jupytext_menu.png
makana_model-0.1.0.data/data/share/jupyter/nbextensions/makana_model/main.js
makana_model-0.1.0.data/data/share/jupyter/nbextensions/makana_model/makanamodel.yaml
makana_model-0.1.0.dist-info/LICENSE
makana_model-0.1.0.dist-info/METADATA
makana_model-0.1.0.dist-info/WHEEL
makana_model-0.1.0.dist-info/top_level.txt
makana_model-0.1.0.dist-info/RECORD
