Metadata-Version: 2.1
Name: makana-model
Version: 0.1.0
Summary: Makana Model.
Home-page: https://github.com/vivek-lakhataria/makana-model
Author: AlpsInfoITSolution
Author-email: vivek.lakhataria@alpsinfo.net
License: BSD-3-Clause
Keywords: Jupyter,JupyterLab,JupyterLab3
Platform: Linux
Platform: Mac OS X
Platform: Windows
Classifier: License :: OSI Approved :: BSD License
Classifier: Programming Language :: Python
Classifier: Programming Language :: Python :: 3
Classifier: Programming Language :: Python :: 3.7
Classifier: Programming Language :: Python :: 3.8
Classifier: Programming Language :: Python :: 3.9
Classifier: Programming Language :: Python :: 3.10
Classifier: Framework :: Jupyter
Classifier: Framework :: Jupyter :: JupyterLab
Classifier: Framework :: Jupyter :: JupyterLab :: 3
Classifier: Framework :: Jupyter :: JupyterLab :: Extensions
Classifier: Framework :: Jupyter :: JupyterLab :: Extensions :: Prebuilt
Requires-Python: >=3.7
License-File: LICENSE
Requires-Dist: nbformat
Requires-Dist: pyyaml
Requires-Dist: toml
Requires-Dist: markdown-it-py (~=1.0)
Requires-Dist: mdit-py-plugins
Provides-Extra: myst
Provides-Extra: rst2md
Requires-Dist: sphinx-gallery (~=0.7.0) ; extra == 'rst2md'
Provides-Extra: toml
Requires-Dist: toml ; extra == 'toml'
